packaging_workshop_bif/__init__.py
packaging_workshop_bif/add.py
packaging_workshop_bif-0.1.0.dist-info/METADATA
packaging_workshop_bif-0.1.0.dist-info/WHEEL
packaging_workshop_bif-0.1.0.dist-info/entry_points.txt
packaging_workshop_bif-0.1.0.dist-info/RECORD
