Metadata-Version: 2.4
Name: packaging-workshop-bif
Version: 0.1.0
Summary: Add your description here
Author-email: noord087 <ben.noordijk@wur.nl>
Requires-Python: >=3.10
Requires-Dist: pytest>=8.3.5
Requires-Dist: ruff>=0.11.2
